snplib/__init__.py
snplib/finalreport/__init__.py
snplib/finalreport/_finalreport.py
snplib/format/__init__.py
snplib/format/__settings.py
snplib/format/_plink.py
snplib/format/_snp.py
snplib/parentage/__init__.py
snplib/parentage/_discov.py
snplib/parentage/_isagmark.py
snplib/parentage/_verif.py
snplib/parentage/isag_disc.pl
snplib/parentage/isag_verif.pl
snplib/statistics/__init__.py
snplib/statistics/_callrate.py
snplib/statistics/_freq.py
snplib/statistics/_snphwe.py
snplib-1.2.11.dist-info/LICENSE
snplib-1.2.11.dist-info/METADATA
snplib-1.2.11.dist-info/WHEEL
snplib-1.2.11.dist-info/top_level.txt
snplib-1.2.11.dist-info/RECORD
