Metadata-Version: 2.2
Name: snplib
Version: 1.2.11
Summary: Snptools is a tool for Single Nucleotide Polymorphism (SNP) data processing
Author-email: Igor <igor.loschinin@gmail.com>
License: GNU
Project-URL: Homepage, https://github.com/IgorekLoschinin/snptools
Classifier: Programming Language :: Python :: 3
Classifier: Operating System :: OS Independent
Requires-Python: >=3.10
License-File: LICENSE
Requires-Dist: numpy>=2.2.3
Requires-Dist: pandas>=2.2.3
Requires-Dist: six>=1.17.0
Requires-Dist: swifter>=1.4.0
Requires-Dist: xlrd>=2.0.1
Requires-Dist: XlsxWriter>=3.2.2
Requires-Dist: openpyxl>=3.1.5
Requires-Dist: pydantic>=2.10.6
